all2md/__init__.py
all2md/__main__.py
all2md/_plaintext-exts.json
all2md/api.py
all2md/constants.py
all2md/converter_metadata.py
all2md/converter_registry.py
all2md/dependencies.py
all2md/exceptions.py
all2md/logging_utils.py
all2md/progress.py
all2md/py.typed
all2md/ast/__init__.py
all2md/ast/builder.py
all2md/ast/nodes.py
all2md/ast/sections.py
all2md/ast/serialization.py
all2md/ast/splitting.py
all2md/ast/transforms.py
all2md/ast/utils.py
all2md/ast/visitors.py
all2md/cli/__init__.py
all2md/cli/builder.py
all2md/cli/config.py
all2md/cli/custom_actions.py
all2md/cli/help_formatter.py
all2md/cli/input_items.py
all2md/cli/output.py
all2md/cli/packaging.py
all2md/cli/presets.py
all2md/cli/processors.py
all2md/cli/progress.py
all2md/cli/timing.py
all2md/cli/validation.py
all2md/cli/watch.py
all2md/cli/commands/__init__.py
all2md/cli/commands/completion.py
all2md/cli/commands/config.py
all2md/cli/commands/diff.py
all2md/cli/commands/formats.py
all2md/cli/commands/generate_site.py
all2md/cli/commands/help.py
all2md/cli/commands/search.py
all2md/cli/commands/server.py
all2md/cli/commands/shared.py
all2md/cli/commands/transforms.py
all2md/cli/commands/view.py
all2md/cli/commands/themes/dark.html
all2md/cli/commands/themes/docs.html
all2md/cli/commands/themes/minimal.html
all2md/cli/commands/themes/newspaper.html
all2md/cli/commands/themes/sidebar.html
all2md/diff/__init__.py
all2md/diff/text_diff.py
all2md/diff/renderers/__init__.py
all2md/diff/renderers/html.py
all2md/diff/renderers/json.py
all2md/diff/renderers/unified.py
all2md/mcp/__init__.py
all2md/mcp/__main__.py
all2md/mcp/config.py
all2md/mcp/document_tools.py
all2md/mcp/schemas.py
all2md/mcp/security.py
all2md/mcp/server.py
all2md/mcp/tools.py
all2md/options/__init__.py
all2md/options/archive.py
all2md/options/asciidoc.py
all2md/options/ast_json.py
all2md/options/base.py
all2md/options/bbcode.py
all2md/options/chm.py
all2md/options/common.py
all2md/options/csv.py
all2md/options/docx.py
all2md/options/dokuwiki.py
all2md-1.0.1.dist-info/METADATA
all2md-1.0.1.dist-info/WHEEL
all2md-1.0.1.dist-info/entry_points.txt
all2md-1.0.1.dist-info/licenses/LICENSE
all2md-1.0.1.dist-info/RECORD
