Metadata-Version: 2.4
Name: all2md
Version: 1.0.1
Summary: Rapid, lightweight conversion of various document formats to markdown for LLMs
Project-URL: Homepage, https://github.com/thomas-villani/all2md
Project-URL: Repository, https://github.com/thomas-villani/all2md
Project-URL: Documentation, https://all2md.readthedocs.io/
Project-URL: Issues, https://github.com/thomas-villani/all2md/issues
Project-URL: Changelog, https://github.com/thomas-villani/all2md/blob/main/CHANGELOG.md
Author-email: "Tom Villani, Ph.D." <thomas.villani@njii.com>
License-Expression: MIT
License-File: LICENSE
Keywords: ai,bidirectional,converter,document-conversion,docx,epub,html,llm,markdown,pandoc-alternative,parsing,pdf,pptx
Classifier: Development Status :: 5 - Production/Stable
Classifier: Intended Audience :: Developers
Classifier: License :: OSI Approved :: MIT License
Classifier: Programming Language :: Python :: 3.10
Classifier: Programming Language :: Python :: 3.11
Classifier: Programming Language :: Python :: 3.12
Classifier: Programming Language :: Python :: 3.13
Classifier: Programming Language :: Python :: 3.14
Classifier: Topic :: File Formats
Classifier: Topic :: Office/Business
Classifier: Topic :: Scientific/Engineering :: Artificial Intelligence
Classifier: Topic :: Software Development :: Documentation
Classifier: Topic :: Text Processing
Classifier: Topic :: Text Processing :: Markup
Classifier: Topic :: Utilities
Requires-Python: >=3.10
Requires-Dist: pyyaml>=6.0
Requires-Dist: tomli-w>=1.0.0
Requires-Dist: tomli>=2.0.0; python_version < '3.11'
Requires-Dist: typing-extensions>=4.0.0; python_version < '3.11'
Provides-Extra: all
Requires-Dist: beautifulsoup4>=4.14.2; extra == 'all'
Requires-Dist: chardet>=5.2.0; extra == 'all'
Requires-Dist: defusedxml>=0.7.1; extra == 'all'
Requires-Dist: docutils>=0.20; extra == 'all'
Requires-Dist: ebooklib>=0.19; extra == 'all'
Requires-Dist: extract-msg>=0.37.1; extra == 'all'
Requires-Dist: fastmcp>=2.0.0; extra == 'all'
Requires-Dist: httpx>=0.28.1; extra == 'all'
Requires-Dist: jinja2>=3.1.0; extra == 'all'
Requires-Dist: langdetect>=1.0.9; extra == 'all'
Requires-Dist: mistune>=3.0.0; extra == 'all'
Requires-Dist: mwparserfromhell>=0.7.2; extra == 'all'
Requires-Dist: odfpy>=1.4.1; extra == 'all'
Requires-Dist: openpyxl>=3.1.5; extra == 'all'
Requires-Dist: orgparse>=0.4.20250520; extra == 'all'
Requires-Dist: pillow>=11.3.0; extra == 'all'
Requires-Dist: py7zr>=0.22.0; extra == 'all'
Requires-Dist: pylatexenc>=2.10; extra == 'all'
Requires-Dist: pymupdf>=1.26.5; extra == 'all'
Requires-Dist: pytesseract>=0.3.10; extra == 'all'
Requires-Dist: pyth3>=0.7; extra == 'all'
Requires-Dist: python-docx>=1.2.0; extra == 'all'
Requires-Dist: python-pptx>=1.0.2; extra == 'all'
Requires-Dist: pyyaml>=6.0; extra == 'all'
Requires-Dist: rank-bm25>=0.2.2; extra == 'all'
Requires-Dist: rarfile>=4.2; extra == 'all'
Requires-Dist: readability-lxml>=0.8.1; extra == 'all'
Requires-Dist: reportlab>=4.0.0; extra == 'all'
Requires-Dist: rich>=14.2.0; extra == 'all'
Requires-Dist: textile>=4.0.1; extra == 'all'
Requires-Dist: tqdm>=4.66.0; extra == 'all'
Requires-Dist: watchdog>=4.0.0; extra == 'all'
Provides-Extra: archive
Requires-Dist: py7zr>=0.22.0; extra == 'archive'
Requires-Dist: rarfile>=4.2; extra == 'archive'
Provides-Extra: chm
Requires-Dist: pychm>=0.8.6; extra == 'chm'
Provides-Extra: cli-extras
Requires-Dist: rich>=14.2.0; extra == 'cli-extras'
Requires-Dist: tqdm>=4.66.0; extra == 'cli-extras'
Requires-Dist: watchdog>=4.0.0; extra == 'cli-extras'
Provides-Extra: dev
Requires-Dist: bandit[toml]>=1.9.2; extra == 'dev'
Requires-Dist: beautifulsoup4>=4.14.2; extra == 'dev'
Requires-Dist: black>=25.9.0; extra == 'dev'
Requires-Dist: chardet>=5.2.0; extra == 'dev'
Requires-Dist: defusedxml>=0.7.1; extra == 'dev'
Requires-Dist: docutils>=0.20; extra == 'dev'
Requires-Dist: ebooklib>=0.19; extra == 'dev'
Requires-Dist: extract-msg>=0.37.1; extra == 'dev'
Requires-Dist: fastmcp>=2.0.0; extra == 'dev'
Requires-Dist: html5lib>=1.1; extra == 'dev'
Requires-Dist: httpx>=0.28.1; extra == 'dev'
Requires-Dist: hypothesis>=6.100.0; extra == 'dev'
Requires-Dist: jinja2>=3.1.0; extra == 'dev'
Requires-Dist: langdetect>=1.0.9; extra == 'dev'
Requires-Dist: mistune>=3.0.0; extra == 'dev'
Requires-Dist: mwparserfromhell>=0.7.2; extra == 'dev'
Requires-Dist: mypy>=1.18.2; extra == 'dev'
Requires-Dist: odfpy>=1.4.1; extra == 'dev'
Requires-Dist: openpyxl>=3.1.5; extra == 'dev'
Requires-Dist: orgparse>=0.4.20250520; extra == 'dev'
Requires-Dist: pillow>=11.3.0; extra == 'dev'
Requires-Dist: pre-commit>=4.3.0; extra == 'dev'
Requires-Dist: py7zr>=0.22.0; extra == 'dev'
Requires-Dist: pylatexenc>=2.10; extra == 'dev'
Requires-Dist: pymupdf>=1.26.5; extra == 'dev'
Requires-Dist: pytesseract>=0.3.10; extra == 'dev'
Requires-Dist: pytest-cov>=7.0.0; extra == 'dev'
Requires-Dist: pytest-xdist>=3.8.0; extra == 'dev'
Requires-Dist: pytest>=8.4.2; extra == 'dev'
Requires-Dist: pyth3>=0.7; extra == 'dev'
Requires-Dist: python-docx>=1.2.0; extra == 'dev'
Requires-Dist: python-pptx>=1.0.2; extra == 'dev'
Requires-Dist: pyyaml>=6.0; extra == 'dev'
Requires-Dist: rank-bm25>=0.2.2; extra == 'dev'
Requires-Dist: rarfile>=4.2; extra == 'dev'
Requires-Dist: readability-lxml>=0.8.1; extra == 'dev'
Requires-Dist: reportlab>=4.0.0; extra == 'dev'
Requires-Dist: rich>=14.2.0; extra == 'dev'
Requires-Dist: ruff>=0.14.0; extra == 'dev'
Requires-Dist: sphinx-copybutton>=0.5.2; (python_version >= '3.11') and extra == 'dev'
Requires-Dist: sphinx-rtd-theme>=3.0.2; (python_version >= '3.11') and extra == 'dev'
Requires-Dist: sphinx>=8.2.3; (python_version >= '3.11') and extra == 'dev'
Requires-Dist: syrupy>=4.6.0; extra == 'dev'
Requires-Dist: textile>=4.0.1; extra == 'dev'
Requires-Dist: tqdm>=4.66.0; extra == 'dev'
Requires-Dist: types-beautifulsoup4; extra == 'dev'
Requires-Dist: types-docutils; extra == 'dev'
Requires-Dist: types-lxml; extra == 'dev'
Requires-Dist: types-pillow; extra == 'dev'
Requires-Dist: types-pyyaml>=6.0.12.20250915; extra == 'dev'
Requires-Dist: types-reportlab; extra == 'dev'
Requires-Dist: watchdog>=4.0.0; extra == 'dev'
Provides-Extra: docx
Requires-Dist: python-docx>=1.2.0; extra == 'docx'
Provides-Extra: docx-render
Requires-Dist: python-docx>=1.2.0; extra == 'docx-render'
Provides-Extra: enex
Requires-Dist: defusedxml>=0.7.1; extra == 'enex'
Provides-Extra: epub
Requires-Dist: ebooklib>=0.19; extra == 'epub'
Provides-Extra: fb2
Requires-Dist: defusedxml>=0.7.1; extra == 'fb2'
Provides-Extra: html
Requires-Dist: beautifulsoup4>=4.13.5; extra == 'html'
Requires-Dist: chardet>=5.2.0; extra == 'html'
Requires-Dist: httpx>=0.28.1; extra == 'html'
Provides-Extra: html-readability
Requires-Dist: readability-lxml>=0.8.1; extra == 'html-readability'
Provides-Extra: http
Requires-Dist: httpx>=0.28.1; extra == 'http'
Provides-Extra: langdetect
Requires-Dist: langdetect>=1.0.9; extra == 'langdetect'
Provides-Extra: latex
Requires-Dist: pylatexenc>=2.10; extra == 'latex'
Provides-Extra: markdown
Requires-Dist: chardet>=5.2.0; extra == 'markdown'
Requires-Dist: mistune>=3.0.0; extra == 'markdown'
Provides-Extra: mcp
Requires-Dist: fastmcp>=2.0.0; extra == 'mcp'
Provides-Extra: ocr
Requires-Dist: pillow>=11.3.0; extra == 'ocr'
Requires-Dist: pytesseract>=0.3.10; extra == 'ocr'
Provides-Extra: odf
Requires-Dist: odfpy>=1.4.1; extra == 'odf'
Provides-Extra: openapi
Requires-Dist: pyyaml>=6.0; extra == 'openapi'
Provides-Extra: org
Requires-Dist: chardet>=5.2.0; extra == 'org'
Requires-Dist: orgparse>=0.4.20250520; extra == 'org'
Provides-Extra: outlook
Requires-Dist: extract-msg>=0.37.1; extra == 'outlook'
Provides-Extra: pdf
Requires-Dist: pymupdf>=1.26.5; extra == 'pdf'
Provides-Extra: pdf-render
Requires-Dist: reportlab>=4.0.0; extra == 'pdf-render'
Provides-Extra: pptx
Requires-Dist: defusedxml>=0.7.1; extra == 'pptx'
Requires-Dist: python-pptx>=1.0.2; extra == 'pptx'
Provides-Extra: rst
Requires-Dist: chardet>=5.2.0; extra == 'rst'
Requires-Dist: docutils>=0.20; extra == 'rst'
Provides-Extra: rtf
Requires-Dist: pyth3>=0.7; extra == 'rtf'
Requires-Dist: six>=1.16.0; extra == 'rtf'
Provides-Extra: sanitizer
Requires-Dist: bleach>=6.2.0; extra == 'sanitizer'
Provides-Extra: search
Requires-Dist: faiss-cpu>=1.7.4; extra == 'search'
Requires-Dist: rank-bm25>=0.2.2; extra == 'search'
Requires-Dist: sentence-transformers>=2.2.2; extra == 'search'
Provides-Extra: templates
Requires-Dist: jinja2>=3.1.0; extra == 'templates'
Provides-Extra: textile
Requires-Dist: chardet>=5.2.0; extra == 'textile'
Requires-Dist: textile>=4.0.1; extra == 'textile'
Provides-Extra: wiki
Requires-Dist: chardet>=5.2.0; extra == 'wiki'
Requires-Dist: mwparserfromhell>=0.7.2; extra == 'wiki'
Provides-Extra: xlsx
Requires-Dist: chardet>=5.2.0; extra == 'xlsx'
Requires-Dist: openpyxl>=3.1.5; extra == 'xlsx'
